larkspur/__init__.py
larkspur/benchmarks.py
larkspur/larkspur.py
larkspur/test_larkspur.py
larkspur-0.2.4.dist-info/LICENSE
larkspur-0.2.4.dist-info/WHEEL
larkspur-0.2.4.dist-info/METADATA
larkspur-0.2.4.dist-info/RECORD
